lu77U_SHA256/Custom_Print.py
lu77U_SHA256/Input_Padder.py
lu77U_SHA256/Main.py
lu77U_SHA256/Main_Class.py
lu77U_SHA256/Padded_Parser.py
lu77U_SHA256/Right_Rotator.py
lu77U_SHA256/__init__.py
lu77U_SHA256-1.2.1.dist-info/LICENSE
lu77U_SHA256-1.2.1.dist-info/METADATA
lu77U_SHA256-1.2.1.dist-info/WHEEL
lu77U_SHA256-1.2.1.dist-info/entry_points.txt
lu77U_SHA256-1.2.1.dist-info/top_level.txt
lu77U_SHA256-1.2.1.dist-info/RECORD
