Metadata-Version: 2.2
Name: lu77U-SHA256
Version: 1.2.1
Summary: An Fully Manual SHA-256 Hasher
Home-page: https://github.com/sam-mg/Python-SHA-256-Implementation
Author: Sam MG Harish (lu77_u)
Author-email: sammgharish@gmail.com
License: Apache Software License 2.0
Classifier: Programming Language :: Python :: 3
Classifier: License :: OSI Approved :: Apache Software License
Classifier: Operating System :: OS Independent
License-File: LICENSE
Requires-Dist: click
Dynamic: author
Dynamic: author-email
Dynamic: classifier
Dynamic: description
Dynamic: description-content-type
Dynamic: home-page
Dynamic: license
Dynamic: requires-dist
Dynamic: summary
